pwchecker/__init__.py
pwchecker/pwchecker.py
pwchecker-1.0.0.dist-info/LICENSE
pwchecker-1.0.0.dist-info/METADATA
pwchecker-1.0.0.dist-info/WHEEL
pwchecker-1.0.0.dist-info/entry_points.txt
pwchecker-1.0.0.dist-info/top_level.txt
pwchecker-1.0.0.dist-info/RECORD
