Metadata-Version: 2.1
Name: pwchecker
Version: 1.0.0
Summary: A CLI tool to check password security and if it has been pwned.
Home-page: https://github.com/lenardflx/PwChecker
Author: Lenard Felix
Classifier: Programming Language :: Python :: 3
Classifier: License :: OSI Approved :: MIT License
Classifier: Operating System :: OS Independent
Requires-Python: >=3.6
License-File: LICENSE
Requires-Dist: requests
Requires-Dist: colorama
